{
    
    "2":{
        "name":"Subjects",
        "link":"/subjects",
        "options":[
        {"text":"Maths","url":"/subjects/maths"},
        {"text":"English","url":"/subjects/english"},
        {"text":"Science","url":"/subjects/science"},
        {"text":"Languages","url":"/subjects/languages"},
        {"text":"Humanities","url":"/subjects/humanities"},
        {"text":"Psychology","url":"/subjects/psychology"}
    ]},
    "1":{
        "name":"Coaching & Mentoring",
        "options":[
        {"text":"Support","url":"/mh/Support"},
        {"text":"Why MH","url":"/mh/why"},
        {"text":"Types of MH","url":"/mh/types"}
    ]},

    "3":{
        "link":"/tutors",
        "name":"Tutors",
        "options":[]},
    "4":{
        "name": "Jobs",
        "link":"/jobs",
        "options":[]
    },
    "0":{
        "name": "Home",
        "link":"/enm",
        "options":[]
    },   
    "5":{
        "name":"Exams",
        "link":"/exams",
        "options":[
        {"text":"Maths","url":"/exams/maths"},
        {"text":"English","url":"/exams/english"},
        {"text":"Science","url":"/exams/science"},
        {"text":"Languages","url":"/exams/languages"},
        {"text":"Humanities","url":"/exams/humanities"},
        {"text":"Psychology","url":"/exams/psychology"}
    ]}     
}